lab1/collatz.sv
module collatz( input logic         clk,   // Clock
		input logic 	    go,    // Load value from n; start iterating
		input logic  [31:0] n,     // Start value; only read when go = 1
		output logic [31:0] dout,  // Iteration value: true after go = 1
		output logic 	    done); // True when dout reaches 1

   /* Replace this comment and the code below with your solution */
   // always_ff @(posedge clk) begin
   //   done <= go;
   //   dout <= n;
   // end
   /* Replace this comment and the code above with your solution */

   always_ff @(posedge clk) begin
      if (go == 1) begin
         dout <= n;
         done <= 0;
      end else if (done == 1) begin
         dout <= dout;
         done <= done;
      end else if (dout == 1) begin
         dout <= dout;
         done <= done;
      end else if (dout[0] == 0) begin
         dout <= dout / 2;

         if (dout / 2 == 1)
            done <= 1;
      end else begin
         dout <= dout * 3 + 1;

         if (dout * 3 + 1 == 1)
            done <= 1;
      end
   end

endmodule

lab1/range.sv
module range
   #(parameter
     RAM_WORDS = 16,            // Number of counts to store in RAM
     RAM_ADDR_BITS = 4)         // Number of RAM address bits
   (input logic         clk,    // Clock
    input logic 	go,     // Read start and start testing
    input logic [31:0] 	start,  // Number to start from or count to read
    output logic 	done,   // True once memory is filled
    output logic [15:0] count); // Iteration count once finished

   logic 		cgo;    // "go" for the Collatz iterator
   logic                cdone;  // "done" from the Collatz iterator
   logic [31:0] 	n;      // number to start the Collatz iterator

// verilator lint_off PINCONNECTEMPTY
   
   // Instantiate the Collatz iterator
   collatz c1(.clk(clk),
	      .go(cgo),
	      .n(n),
	      .done(cdone),
	      .dout());

   logic [RAM_ADDR_BITS - 1:0] 	 num;         // The RAM address to write
   // logic 			 running = 0; // True during the iterations

   /* Replace this comment and the code below with your solution,
      which should generate running, done, cgo, n, num, we, and din */
   // assign done = cdone;
   // assign cgo = go;
   // assign n = start;
   // assign din = 16'h0;
   // assign num = 0;
   // assign we = running;   
   /* Replace this comment and the code above with your solution */

   logic 			 we;                       // enable write    
   logic [15:0] 		 din;                   // Data to write
   logic [15:0] 		 mem[RAM_WORDS - 1:0];  // The RAM itself

   logic running;
   logic starting;
   logic counting;
   logic writing;
   logic advancing;
   logic [31:0] index;
   logic wait_cycle; // one cycle delay after asserting cgo
   
   logic [31:0] base;  // store start val
   assign n = base + index; // cur val sent to collatz when cgo is pulsed

   logic [RAM_ADDR_BITS - 1:0] 	 addr;   // read addr
   assign addr = start[RAM_ADDR_BITS-1:0];
   // assign addr = we ? num : start[RAM_ADDR_BITS-1:0];


   always_ff @(posedge clk) begin
      cgo <= 0;
      done <= 0;
      we <= 0;

      if (running == 0) begin
         if (go == 1) begin
            running <= 1;
            starting <= 1;
            counting <= 0;
            writing <= 0;
            advancing <= 0;
            wait_cycle <= 0;   // clear wait state for new run


            base <= start;
            index <= 0;
            num <= 0;
         end
      end else if (starting == 1) begin
         starting <= 0;
         wait_cycle <= 1;
         cgo <= 1;      
         din <= 1;
      end else if (wait_cycle == 1) begin
         wait_cycle <= 0;
         counting <= 1;
      end else if (counting == 1) begin
         if (cdone == 0) begin
            din <= din + 1;
         end else begin
            counting <= 0;
            writing <= 1;
         end
      end else if (writing == 1) begin
         we <= 1;

         writing <= 0;
         advancing <= 1;
      end else if (advancing == 1) begin
         if (index == RAM_WORDS - 1) begin
            advancing <= 0;
            running <= 0;

            done <= 1;
         end else begin
            advancing <= 0;
            starting <= 1;

            index <= index + 1;
            num <= num + 1;
            din <= 0;  // resets counter for next number
         end
      end 
   end

   
   always_ff @(posedge clk) begin
   if (we) mem[num] <= din;   
   count <= mem[addr];       
   end


endmodule

lab1/range.vcd
$version Generated by VerilatedVcd $end
$timescale 1ps $end
 $scope module TOP $end
  $var wire 1 B clk $end
  $var wire 1 C go $end
  $var wire 32 D start [31:0] $end
  $var wire 1 E done $end
  $var wire 16 F count [15:0] $end
  $scope module range $end
   $var wire 32 H RAM_WORDS [31:0] $end
   $var wire 32 I RAM_ADDR_BITS [31:0] $end
   $var wire 1 B clk $end
   $var wire 1 C go $end
   $var wire 32 D start [31:0] $end
   $var wire 1 E done $end
   $var wire 16 F count [15:0] $end
   $var wire 1 # cgo $end
   $var wire 1 $ cdone $end
   $var wire 32 % n [31:0] $end
   $var wire 4 & num [3:0] $end
   $var wire 1 ' we $end
   $var wire 16 ( din [15:0] $end
   $var wire 16 ) mem[0] [15:0] $end
   $var wire 16 * mem[1] [15:0] $end
   $var wire 16 + mem[2] [15:0] $end
   $var wire 16 , mem[3] [15:0] $end
   $var wire 16 - mem[4] [15:0] $end
   $var wire 16 . mem[5] [15:0] $end
   $var wire 16 / mem[6] [15:0] $end
   $var wire 16 0 mem[7] [15:0] $end
   $var wire 16 1 mem[8] [15:0] $end
   $var wire 16 2 mem[9] [15:0] $end
   $var wire 16 3 mem[10] [15:0] $end
   $var wire 16 4 mem[11] [15:0] $end
   $var wire 16 5 mem[12] [15:0] $end
   $var wire 16 6 mem[13] [15:0] $end
   $var wire 16 7 mem[14] [15:0] $end
   $var wire 16 8 mem[15] [15:0] $end
   $var wire 1 9 running $end
   $var wire 1 : starting $end
   $var wire 1 ; counting $end
   $var wire 1 < writing $end
   $var wire 1 = advancing $end
   $var wire 32 > index [31:0] $end
   $var wire 1 ? wait_cycle $end
   $var wire 32 @ base [31:0] $end
   $var wire 4 G addr [3:0] $end
   $scope module c1 $end
    $var wire 1 B clk $end
    $var wire 1 # go $end
    $var wire 32 % n [31:0] $end
    $var wire 32 A dout [31:0] $end
    $var wire 1 $ done $end
   $upscope $end
  $upscope $end
 $upscope $end
$enddefinitions $end


#0
0#
0$
b00000000000000000000000000000000 %
b0000 &
0'
b0000000000000000 (
b0000000000000000 )
b0000000000000000 *
b0000000000000000 +
b0000000000000000 ,
b0000000000000000 -
b0000000000000000 .
b0000000000000000 /
b0000000000000000 0
b0000000000000000 1
b0000000000000000 2
b0000000000000000 3
b0000000000000000 4
b0000000000000000 5
b0000000000000000 6
b0000000000000000 7
b0000000000000000 8
09
0:
0;
0<
0=
b00000000000000000000000000000000 >
0?
b00000000000000000000000000000000 @
b00000000000000000000000000000000 A
0B
1C
b00000000000000000000000000000111 D
0E
b0000000000000000 F
b0111 G
b00000000000000000000000000010000 H
b00000000000000000000000000000100 I
#10
b00000000000000000000000000000111 %
19
1:
b00000000000000000000000000000111 @
1B
#20
0B
#30
1#
b0000000000000001 (
0:
1?
1B
#40
0B
0C
#50
0#
1;
0?
b00000000000000000000000000000111 A
1B
#60
0B
#70
b0000000000000010 (
b00000000000000000000000000010110 A
1B
#80
0B
#90
b0000000000000011 (
b00000000000000000000000000001011 A
1B
#100
0B
#110
b0000000000000100 (
b00000000000000000000000000100010 A
1B
#120
0B
#130
b0000000000000101 (
b00000000000000000000000000010001 A
1B
#140
0B
#150
b0000000000000110 (
b00000000000000000000000000110100 A
1B
#160
0B
#170
b0000000000000111 (
b00000000000000000000000000011010 A
1B
#180
0B
#190
b0000000000001000 (
b00000000000000000000000000001101 A
1B
#200
0B
#210
b0000000000001001 (
b00000000000000000000000000101000 A
1B
#220
0B
#230
b0000000000001010 (
b00000000000000000000000000010100 A
1B
#240
0B
#250
b0000000000001011 (
b00000000000000000000000000001010 A
1B
#260
0B
#270
b0000000000001100 (
b00000000000000000000000000000101 A
1B
#280
0B
#290
b0000000000001101 (
b00000000000000000000000000010000 A
1B
#300
0B
#310
b0000000000001110 (
b00000000000000000000000000001000 A
1B
#320
0B
#330
b0000000000001111 (
b00000000000000000000000000000100 A
1B
#340
0B
#350
b0000000000010000 (
b00000000000000000000000000000010 A
1B
#360
0B
#370
1$
b0000000000010001 (
b00000000000000000000000000000001 A
1B
#380
0B
#390
0;
1<
1B
#400
0B
#410
1'
0<
1=
1B
#420
0B
#430
b00000000000000000000000000001000 %
b0001 &
0'
b0000000000000000 (
b0000000000010001 )
1:
0=
b00000000000000000000000000000001 >
1B
#440
0B
#450
1#
b0000000000000001 (
0:
1?
1B
#460
0B
#470
0#
0$
1;
0?
b00000000000000000000000000001000 A
1B
#480
0B
#490
b0000000000000010 (
b00000000000000000000000000000100 A
1B
#500
0B
#510
b0000000000000011 (
b00000000000000000000000000000010 A
1B
#520
0B
#530
1$
b0000000000000100 (
b00000000000000000000000000000001 A
1B
#540
0B
#550
0;
1<
1B
#560
0B
#570
1'
0<
1=
1B
#580
0B
#590
b00000000000000000000000000001001 %
b0010 &
0'
b0000000000000000 (
b0000000000000100 *
1:
0=
b00000000000000000000000000000010 >
1B
#600
0B
#610
1#
b0000000000000001 (
0:
1?
1B
#620
0B
#630
0#
0$
1;
0?
b00000000000000000000000000001001 A
1B
#640
0B
#650
b0000000000000010 (
b00000000000000000000000000011100 A
1B
#660
0B
#670
b0000000000000011 (
b00000000000000000000000000001110 A
1B
#680
0B
#690
b0000000000000100 (
b00000000000000000000000000000111 A
1B
#700
0B
#710
b0000000000000101 (
b00000000000000000000000000010110 A
1B
#720
0B
#730
b0000000000000110 (
b00000000000000000000000000001011 A
1B
#740
0B
#750
b0000000000000111 (
b00000000000000000000000000100010 A
1B
#760
0B
#770
b0000000000001000 (
b00000000000000000000000000010001 A
1B
#780
0B
#790
b0000000000001001 (
b00000000000000000000000000110100 A
1B
#800
0B
#810
b0000000000001010 (
b00000000000000000000000000011010 A
1B
#820
0B
#830
b0000000000001011 (
b00000000000000000000000000001101 A
1B
#840
0B
#850
b0000000000001100 (
b00000000000000000000000000101000 A
1B
#860
0B
#870
b0000000000001101 (
b00000000000000000000000000010100 A
1B
#880
0B
#890
b0000000000001110 (
b00000000000000000000000000001010 A
1B
#900
0B
#910
b0000000000001111 (
b00000000000000000000000000000101 A
1B
#920
0B
#930
b0000000000010000 (
b00000000000000000000000000010000 A
1B
#940
0B
#950
b0000000000010001 (
b00000000000000000000000000001000 A
1B
#960
0B
#970
b0000000000010010 (
b00000000000000000000000000000100 A
1B
#980
0B
#990
b0000000000010011 (
b00000000000000000000000000000010 A
1B
#1000
0B
#1010
1$
b0000000000010100 (
b00000000000000000000000000000001 A
1B
#1020
0B
#1030
0;
1<
1B
#1040
0B
#1050
1'
0<
1=
1B
#1060
0B
#1070
b00000000000000000000000000001010 %
b0011 &
0'
b0000000000000000 (
b0000000000010100 +
1:
0=
b00000000000000000000000000000011 >
1B
#1080
0B
#1090
1#
b0000000000000001 (
0:
1?
1B
#1100
0B
#1110
0#
0$
1;
0?
b00000000000000000000000000001010 A
1B
#1120
0B
#1130
b0000000000000010 (
b00000000000000000000000000000101 A
1B
#1140
0B
#1150
b0000000000000011 (
b00000000000000000000000000010000 A
1B
#1160
0B
#1170
b0000000000000100 (
b00000000000000000000000000001000 A
1B
#1180
0B
#1190
b0000000000000101 (
b00000000000000000000000000000100 A
1B
#1200
0B
#1210
b0000000000000110 (
b00000000000000000000000000000010 A
1B
#1220
0B
#1230
1$
b0000000000000111 (
b00000000000000000000000000000001 A
1B
#1240
0B
#1250
0;
1<
1B
#1260
0B
#1270
1'
0<
1=
1B
#1280
0B
#1290
b00000000000000000000000000001011 %
b0100 &
0'
b0000000000000000 (
b0000000000000111 ,
1:
0=
b00000000000000000000000000000100 >
1B
#1300
0B
#1310
1#
b0000000000000001 (
0:
1?
1B
#1320
0B
#1330
0#
0$
1;
0?
b00000000000000000000000000001011 A
1B
#1340
0B
#1350
b0000000000000010 (
b00000000000000000000000000100010 A
1B
#1360
0B
#1370
b0000000000000011 (
b00000000000000000000000000010001 A
1B
#1380
0B
#1390
b0000000000000100 (
b00000000000000000000000000110100 A
1B
#1400
0B
#1410
b0000000000000101 (
b00000000000000000000000000011010 A
1B
#1420
0B
#1430
b0000000000000110 (
b00000000000000000000000000001101 A
1B
#1440
0B
#1450
b0000000000000111 (
b00000000000000000000000000101000 A
1B
#1460
0B
#1470
b0000000000001000 (
b00000000000000000000000000010100 A
1B
#1480
0B
#1490
b0000000000001001 (
b00000000000000000000000000001010 A
1B
#1500
0B
#1510
b0000000000001010 (
b00000000000000000000000000000101 A
1B
#1520
0B
#1530
b0000000000001011 (
b00000000000000000000000000010000 A
1B
#1540
0B
#1550
b0000000000001100 (
b00000000000000000000000000001000 A
1B
#1560
0B
#1570
b0000000000001101 (
b00000000000000000000000000000100 A
1B
#1580
0B
#1590
b0000000000001110 (
b00000000000000000000000000000010 A
1B
#1600
0B
#1610
1$
b0000000000001111 (
b00000000000000000000000000000001 A
1B
#1620
0B
#1630
0;
1<
1B
#1640
0B
#1650
1'
0<
1=
1B
#1660
0B
#1670
b00000000000000000000000000001100 %
b0101 &
0'
b0000000000000000 (
b0000000000001111 -
1:
0=
b00000000000000000000000000000101 >
1B
#1680
0B
#1690
1#
b0000000000000001 (
0:
1?
1B
#1700
0B
#1710
0#
0$
1;
0?
b00000000000000000000000000001100 A
1B
#1720
0B
#1730
b0000000000000010 (
b00000000000000000000000000000110 A
1B
#1740
0B
#1750
b0000000000000011 (
b00000000000000000000000000000011 A
1B
#1760
0B
#1770
b0000000000000100 (
b00000000000000000000000000001010 A
1B
#1780
0B
#1790
b0000000000000101 (
b00000000000000000000000000000101 A
1B
#1800
0B
#1810
b0000000000000110 (
b00000000000000000000000000010000 A
1B
#1820
0B
#1830
b0000000000000111 (
b00000000000000000000000000001000 A
1B
#1840
0B
#1850
b0000000000001000 (
b00000000000000000000000000000100 A
1B
#1860
0B
#1870
b0000000000001001 (
b00000000000000000000000000000010 A
1B
#1880
0B
#1890
1$
b0000000000001010 (
b00000000000000000000000000000001 A
1B
#1900
0B
#1910
0;
1<
1B
#1920
0B
#1930
1'
0<
1=
1B
#1940
0B
#1950
b00000000000000000000000000001101 %
b0110 &
0'
b0000000000000000 (
b0000000000001010 .
1:
0=
b00000000000000000000000000000110 >
1B
#1960
0B
#1970
1#
b0000000000000001 (
0:
1?
1B
#1980
0B
#1990
0#
0$
1;
0?
b00000000000000000000000000001101 A
1B
#2000
0B
#2010
b0000000000000010 (
b00000000000000000000000000101000 A
1B
#2020
0B
#2030
b0000000000000011 (
b00000000000000000000000000010100 A
1B
#2040
0B
#2050
b0000000000000100 (
b00000000000000000000000000001010 A
1B
#2060
0B
#2070
b0000000000000101 (
b00000000000000000000000000000101 A
1B
#2080
0B
#2090
b0000000000000110 (
b00000000000000000000000000010000 A
1B
#2100
0B
#2110
b0000000000000111 (
b00000000000000000000000000001000 A
1B
#2120
0B
#2130
b0000000000001000 (
b00000000000000000000000000000100 A
1B
#2140
0B
#2150
b0000000000001001 (
b00000000000000000000000000000010 A
1B
#2160
0B
#2170
1$
b0000000000001010 (
b00000000000000000000000000000001 A
1B
#2180
0B
#2190
0;
1<
1B
#2200
0B
#2210
1'
0<
1=
1B
#2220
0B
#2230
b00000000000000000000000000001110 %
b0111 &
0'
b0000000000000000 (
b0000000000001010 /
1:
0=
b00000000000000000000000000000111 >
1B
#2240
0B
#2250
1#
b0000000000000001 (
0:
1?
1B
#2260
0B
#2270
0#
0$
1;
0?
b00000000000000000000000000001110 A
1B
#2280
0B
#2290
b0000000000000010 (
b00000000000000000000000000000111 A
1B
#2300
0B
#2310
b0000000000000011 (
b00000000000000000000000000010110 A
1B
#2320
0B
#2330
b0000000000000100 (
b00000000000000000000000000001011 A
1B
#2340
0B
#2350
b0000000000000101 (
b00000000000000000000000000100010 A
1B
#2360
0B
#2370
b0000000000000110 (
b00000000000000000000000000010001 A
1B
#2380
0B
#2390
b0000000000000111 (
b00000000000000000000000000110100 A
1B
#2400
0B
#2410
b0000000000001000 (
b00000000000000000000000000011010 A
1B
#2420
0B
#2430
b0000000000001001 (
b00000000000000000000000000001101 A
1B
#2440
0B
#2450
b0000000000001010 (
b00000000000000000000000000101000 A
1B
#2460
0B
#2470
b0000000000001011 (
b00000000000000000000000000010100 A
1B
#2480
0B
#2490
b0000000000001100 (
b00000000000000000000000000001010 A
1B
#2500
0B
#2510
b0000000000001101 (
b00000000000000000000000000000101 A
1B
#2520
0B
#2530
b0000000000001110 (
b00000000000000000000000000010000 A
1B
#2540
0B
#2550
b0000000000001111 (
b00000000000000000000000000001000 A
1B
#2560
0B
#2570
b0000000000010000 (
b00000000000000000000000000000100 A
1B
#2580
0B
#2590
b0000000000010001 (
b00000000000000000000000000000010 A
1B
#2600
0B
#2610
1$
b0000000000010010 (
b00000000000000000000000000000001 A
1B
#2620
0B
#2630
0;
1<
1B
#2640
0B
#2650
1'
0<
1=
1B
#2660
0B
#2670
b00000000000000000000000000001111 %
b1000 &
0'
b0000000000000000 (
b0000000000010010 0
1:
0=
b00000000000000000000000000001000 >
1B
#2680
0B
#2690
1#
b0000000000000001 (
0:
1?
1B
b0000000000010010 F
#2700
0B
#2710
0#
0$
1;
0?
b00000000000000000000000000001111 A
1B
#2720
0B
#2730
b0000000000000010 (
b00000000000000000000000000101110 A
1B
#2740
0B
#2750
b0000000000000011 (
b00000000000000000000000000010111 A
1B
#2760
0B
#2770
b0000000000000100 (
b00000000000000000000000001000110 A
1B
#2780
0B
#2790
b0000000000000101 (
b00000000000000000000000000100011 A
1B
#2800
0B
#2810
b0000000000000110 (
b00000000000000000000000001101010 A
1B
#2820
0B
#2830
b0000000000000111 (
b00000000000000000000000000110101 A
1B
#2840
0B
#2850
b0000000000001000 (
b00000000000000000000000010100000 A
1B
#2860
0B
#2870
b0000000000001001 (
b00000000000000000000000001010000 A
1B
#2880
0B
#2890
b0000000000001010 (
b00000000000000000000000000101000 A
1B
#2900
0B
#2910
b0000000000001011 (
b00000000000000000000000000010100 A
1B
#2920
0B
#2930
b0000000000001100 (
b00000000000000000000000000001010 A
1B
#2940
0B
#2950
b0000000000001101 (
b00000000000000000000000000000101 A
1B
#2960
0B
#2970
b0000000000001110 (
b00000000000000000000000000010000 A
1B
#2980
0B
#2990
b0000000000001111 (
b00000000000000000000000000001000 A
1B
#3000
0B
#3010
b0000000000010000 (
b00000000000000000000000000000100 A
1B
#3020
0B
#3030
b0000000000010001 (
b00000000000000000000000000000010 A
1B
#3040
0B
#3050
1$
b0000000000010010 (
b00000000000000000000000000000001 A
1B
#3060
0B
#3070
0;
1<
1B
#3080
0B
#3090
1'
0<
1=
1B
#3100
0B
#3110
b00000000000000000000000000010000 %
b1001 &
0'
b0000000000000000 (
b0000000000010010 1
1:
0=
b00000000000000000000000000001001 >
1B
#3120
0B
#3130
1#
b0000000000000001 (
0:
1?
1B
#3140
0B
#3150
0#
0$
1;
0?
b00000000000000000000000000010000 A
1B
#3160
0B
#3170
b0000000000000010 (
b00000000000000000000000000001000 A
1B
#3180
0B
#3190
b0000000000000011 (
b00000000000000000000000000000100 A
1B
#3200
0B
#3210
b0000000000000100 (
b00000000000000000000000000000010 A
1B
#3220
0B
#3230
1$
b0000000000000101 (
b00000000000000000000000000000001 A
1B
#3240
0B
#3250
0;
1<
1B
#3260
0B
#3270
1'
0<
1=
1B
#3280
0B
#3290
b00000000000000000000000000010001 %
b1010 &
0'
b0000000000000000 (
b0000000000000101 2
1:
0=
b00000000000000000000000000001010 >
1B
#3300
0B
#3310
1#
b0000000000000001 (
0:
1?
1B
#3320
0B
#3330
0#
0$
1;
0?
b00000000000000000000000000010001 A
1B
#3340
0B
#3350
b0000000000000010 (
b00000000000000000000000000110100 A
1B
#3360
0B
#3370
b0000000000000011 (
b00000000000000000000000000011010 A
1B
#3380
0B
#3390
b0000000000000100 (
b00000000000000000000000000001101 A
1B
#3400
0B
#3410
b0000000000000101 (
b00000000000000000000000000101000 A
1B
#3420
0B
#3430
b0000000000000110 (
b00000000000000000000000000010100 A
1B
#3440
0B
#3450
b0000000000000111 (
b00000000000000000000000000001010 A
1B
#3460
0B
#3470
b0000000000001000 (
b00000000000000000000000000000101 A
1B
#3480
0B
#3490
b0000000000001001 (
b00000000000000000000000000010000 A
1B
#3500
0B
#3510
b0000000000001010 (
b00000000000000000000000000001000 A
1B
#3520
0B
#3530
b0000000000001011 (
b00000000000000000000000000000100 A
1B
#3540
0B
#3550
b0000000000001100 (
b00000000000000000000000000000010 A
1B
#3560
0B
#3570
1$
b0000000000001101 (
b00000000000000000000000000000001 A
1B
#3580
0B
#3590
0;
1<
1B
#3600
0B
#3610
1'
0<
1=
1B
#3620
0B
#3630
b00000000000000000000000000010010 %
b1011 &
0'
b0000000000000000 (
b0000000000001101 3
1:
0=
b00000000000000000000000000001011 >
1B
#3640
0B
#3650
1#
b0000000000000001 (
0:
1?
1B
#3660
0B
#3670
0#
0$
1;
0?
b00000000000000000000000000010010 A
1B
#3680
0B
#3690
b0000000000000010 (
b00000000000000000000000000001001 A
1B
#3700
0B
#3710
b0000000000000011 (
b00000000000000000000000000011100 A
1B
#3720
0B
#3730
b0000000000000100 (
b00000000000000000000000000001110 A
1B
#3740
0B
#3750
b0000000000000101 (
b00000000000000000000000000000111 A
1B
#3760
0B
#3770
b0000000000000110 (
b00000000000000000000000000010110 A
1B
#3780
0B
#3790
b0000000000000111 (
b00000000000000000000000000001011 A
1B
#3800
0B
#3810
b0000000000001000 (
b00000000000000000000000000100010 A
1B
#3820
0B
#3830
b0000000000001001 (
b00000000000000000000000000010001 A
1B
#3840
0B
#3850
b0000000000001010 (
b00000000000000000000000000110100 A
1B
#3860
0B
#3870
b0000000000001011 (
b00000000000000000000000000011010 A
1B
#3880
0B
#3890
b0000000000001100 (
b00000000000000000000000000001101 A
1B
#3900
0B
#3910
b0000000000001101 (
b00000000000000000000000000101000 A
1B
#3920
0B
#3930
b0000000000001110 (
b00000000000000000000000000010100 A
1B
#3940
0B
#3950
b0000000000001111 (
b00000000000000000000000000001010 A
1B
#3960
0B
#3970
b0000000000010000 (
b00000000000000000000000000000101 A
1B
#3980
0B
#3990
b0000000000010001 (
b00000000000000000000000000010000 A
1B
#4000
0B
#4010
b0000000000010010 (
b00000000000000000000000000001000 A
1B
#4020
0B
#4030
b0000000000010011 (
b00000000000000000000000000000100 A
1B
#4040
0B
#4050
b0000000000010100 (
b00000000000000000000000000000010 A
1B
#4060
0B
#4070
1$
b0000000000010101 (
b00000000000000000000000000000001 A
1B
#4080
0B
#4090
0;
1<
1B
#4100
0B
#4110
1'
0<
1=
1B
#4120
0B
#4130
b00000000000000000000000000010011 %
b1100 &
0'
b0000000000000000 (
b0000000000010101 4
1:
0=
b00000000000000000000000000001100 >
1B
#4140
0B
#4150
1#
b0000000000000001 (
0:
1?
1B
#4160
0B
#4170
0#
0$
1;
0?
b00000000000000000000000000010011 A
1B
#4180
0B
#4190
b0000000000000010 (
b00000000000000000000000000111010 A
1B
#4200
0B
#4210
b0000000000000011 (
b00000000000000000000000000011101 A
1B
#4220
0B
#4230
b0000000000000100 (
b00000000000000000000000001011000 A
1B
#4240
0B
#4250
b0000000000000101 (
b00000000000000000000000000101100 A
1B
#4260
0B
#4270
b0000000000000110 (
b00000000000000000000000000010110 A
1B
#4280
0B
#4290
b0000000000000111 (
b00000000000000000000000000001011 A
1B
#4300
0B
#4310
b0000000000001000 (
b00000000000000000000000000100010 A
1B
#4320
0B
#4330
b0000000000001001 (
b00000000000000000000000000010001 A
1B
#4340
0B
#4350
b0000000000001010 (
b00000000000000000000000000110100 A
1B
#4360
0B
#4370
b0000000000001011 (
b00000000000000000000000000011010 A
1B
#4380
0B
#4390
b0000000000001100 (
b00000000000000000000000000001101 A
1B
#4400
0B
#4410
b0000000000001101 (
b00000000000000000000000000101000 A
1B
#4420
0B
#4430
b0000000000001110 (
b00000000000000000000000000010100 A
1B
#4440
0B
#4450
b0000000000001111 (
b00000000000000000000000000001010 A
1B
#4460
0B
#4470
b0000000000010000 (
b00000000000000000000000000000101 A
1B
#4480
0B
#4490
b0000000000010001 (
b00000000000000000000000000010000 A
1B
#4500
0B
#4510
b0000000000010010 (
b00000000000000000000000000001000 A
1B
#4520
0B
#4530
b0000000000010011 (
b00000000000000000000000000000100 A
1B
#4540
0B
#4550
b0000000000010100 (
b00000000000000000000000000000010 A
1B
#4560
0B
#4570
1$
b0000000000010101 (
b00000000000000000000000000000001 A
1B
#4580
0B
#4590
0;
1<
1B
#4600
0B
#4610
1'
0<
1=
1B
#4620
0B
#4630
b00000000000000000000000000010100 %
b1101 &
0'
b0000000000000000 (
b0000000000010101 5
1:
0=
b00000000000000000000000000001101 >
1B
#4640
0B
#4650
1#
b0000000000000001 (
0:
1?
1B
#4660
0B
#4670
0#
0$
1;
0?
b00000000000000000000000000010100 A
1B
#4680
0B
#4690
b0000000000000010 (
b00000000000000000000000000001010 A
1B
#4700
0B
#4710
b0000000000000011 (
b00000000000000000000000000000101 A
1B
#4720
0B
#4730
b0000000000000100 (
b00000000000000000000000000010000 A
1B
#4740
0B
#4750
b0000000000000101 (
b00000000000000000000000000001000 A
1B
#4760
0B
#4770
b0000000000000110 (
b00000000000000000000000000000100 A
1B
#4780
0B
#4790
b0000000000000111 (
b00000000000000000000000000000010 A
1B
#4800
0B
#4810
1$
b0000000000001000 (
b00000000000000000000000000000001 A
1B
#4820
0B
#4830
0;
1<
1B
#4840
0B
#4850
1'
0<
1=
1B
#4860
0B
#4870
b00000000000000000000000000010101 %
b1110 &
0'
b0000000000000000 (
b0000000000001000 6
1:
0=
b00000000000000000000000000001110 >
1B
#4880
0B
#4890
1#
b0000000000000001 (
0:
1?
1B
#4900
0B
#4910
0#
0$
1;
0?
b00000000000000000000000000010101 A
1B
#4920
0B
#4930
b0000000000000010 (
b00000000000000000000000001000000 A
1B
#4940
0B
#4950
b0000000000000011 (
b00000000000000000000000000100000 A
1B
#4960
0B
#4970
b0000000000000100 (
b00000000000000000000000000010000 A
1B
#4980
0B
#4990
b0000000000000101 (
b00000000000000000000000000001000 A
1B
#5000
0B
#5010
b0000000000000110 (
b00000000000000000000000000000100 A
1B
#5020
0B
#5030
b0000000000000111 (
b00000000000000000000000000000010 A
1B
#5040
0B
#5050
1$
b0000000000001000 (
b00000000000000000000000000000001 A
1B
#5060
0B
#5070
0;
1<
1B
#5080
0B
#5090
1'
0<
1=
1B
#5100
0B
#5110
b00000000000000000000000000010110 %
b1111 &
0'
b0000000000000000 (
b0000000000001000 7
1:
0=
b00000000000000000000000000001111 >
1B
#5120
0B
#5130
1#
b0000000000000001 (
0:
1?
1B
#5140
0B
#5150
0#
0$
1;
0?
b00000000000000000000000000010110 A
1B
#5160
0B
#5170
b0000000000000010 (
b00000000000000000000000000001011 A
1B
#5180
0B
#5190
b0000000000000011 (
b00000000000000000000000000100010 A
1B
#5200
0B
#5210
b0000000000000100 (
b00000000000000000000000000010001 A
1B
#5220
0B
#5230
b0000000000000101 (
b00000000000000000000000000110100 A
1B
#5240
0B
#5250
b0000000000000110 (
b00000000000000000000000000011010 A
1B
#5260
0B
#5270
b0000000000000111 (
b00000000000000000000000000001101 A
1B
#5280
0B
#5290
b0000000000001000 (
b00000000000000000000000000101000 A
1B
#5300
0B
#5310
b0000000000001001 (
b00000000000000000000000000010100 A
1B
#5320
0B
#5330
b0000000000001010 (
b00000000000000000000000000001010 A
1B
#5340
0B
#5350
b0000000000001011 (
b00000000000000000000000000000101 A
1B
#5360
0B
#5370
b0000000000001100 (
b00000000000000000000000000010000 A
1B
#5380
0B
#5390
b0000000000001101 (
b00000000000000000000000000001000 A
1B
#5400
0B
#5410
b0000000000001110 (
b00000000000000000000000000000100 A
1B
#5420
0B
#5430
b0000000000001111 (
b00000000000000000000000000000010 A
1B
#5440
0B
#5450
1$
b0000000000010000 (
b00000000000000000000000000000001 A
1B
#5460
0B
#5470
0;
1<
1B
#5480
0B
#5490
1'
0<
1=
1B
#5500
0B
#5510
0'
b0000000000010000 8
09
0=
1B
1E
#5520
0B
b00000000000000000000000000000000 D
b0000 G
#5530
1B
0E
b0000000000010001 F
#5540
0B
b00000000000000000000000000000001 D
b0001 G
#5550
1B
b0000000000000100 F
#5560
0B
b00000000000000000000000000000010 D
b0010 G
#5570
1B
b0000000000010100 F
#5580
0B
b00000000000000000000000000000011 D
b0011 G
#5590
1B
b0000000000000111 F
#5600
0B
b00000000000000000000000000000100 D
b0100 G
#5610
1B
b0000000000001111 F
#5620
0B
b00000000000000000000000000000101 D
b0101 G
#5630
1B
b0000000000001010 F
#5640
0B
b00000000000000000000000000000110 D
b0110 G
#5650
1B
#5660
0B
b00000000000000000000000000000111 D
b0111 G
#5670
1B
b0000000000010010 F
#5680
0B
b00000000000000000000000000001000 D
b1000 G
#5690
1B
#5700
0B
b00000000000000000000000000001001 D
b1001 G
#5710
1B
b0000000000000101 F
#5720
0B
b00000000000000000000000000001010 D
b1010 G
#5730
1B
b0000000000001101 F
#5740
0B
b00000000000000000000000000001011 D
b1011 G
#5750
1B
b0000000000010101 F
#5760
0B
b00000000000000000000000000001100 D
b1100 G
#5770
1B
#5780
0B
b00000000000000000000000000001101 D
b1101 G
#5790
1B
b0000000000001000 F
#5800
0B
b00000000000000000000000000001110 D
b1110 G
#5810
1B
#5820
0B
b00000000000000000000000000001111 D
b1111 G
#5830
1B
b0000000000010000 F
